apple_news_to_sqlite/__init__.py
apple_news_to_sqlite/__main__.py
apple_news_to_sqlite/cli.py
apple_news_to_sqlite/news.py
apple_news_to_sqlite/version.py
apple_news_to_sqlite-0.5.2.dist-info/LICENSE
apple_news_to_sqlite-0.5.2.dist-info/WHEEL
apple_news_to_sqlite-0.5.2.dist-info/entry_points.txt
apple_news_to_sqlite-0.5.2.dist-info/METADATA
apple_news_to_sqlite-0.5.2.dist-info/RECORD
