Metadata-Version: 2.1
Name: apple-news-to-sqlite
Version: 0.5.2
Summary: Export "Saved Stories" from Apple News to SQLite
Home-page: https://github.com/RhetTbull/apple-news-to-sqlite
License: MIT
Keywords: cli,mac,macos,sqlite,news,apple
Author: Rhet Turnbull
Author-email: rturnbull+git@gmail.com
Requires-Python: >=3.9,<4.0
Classifier: License :: OSI Approved :: MIT License
Classifier: Programming Language :: Python :: 3
Classifier: Programming Language :: Python :: 3.9
Classifier: Programming Language :: Python :: 3.10
Classifier: Programming Language :: Python :: 3.11
Requires-Dist: bs4 (>=0.0.1,<0.0.2)
Requires-Dist: click (>=8.1.3,<9.0.0)
Requires-Dist: requests (>=2.28.2,<3.0.0)
Requires-Dist: sqlite-utils (>=3.30,<4.0)
Project-URL: Repository, https://github.com/RhetTbull/apple-news-to-sqlite
